unipdb_mapper/__init__.py
unipdb_mapper/__main__.py
unipdb_mapper/id_mapper.py
unipdb_mapper/residue_mapper.py
unipdb_mapper/utilities.py
unipdb_mapper-1.0.0.dist-info/METADATA
unipdb_mapper-1.0.0.dist-info/WHEEL
unipdb_mapper-1.0.0.dist-info/entry_points.txt
unipdb_mapper-1.0.0.dist-info/licenses/LICENSE
unipdb_mapper-1.0.0.dist-info/RECORD
