Metadata-Version: 2.4
Name: unipdb_mapper
Version: 1.0.0
Summary: Python Package for residue mapping between UniProt and PDB entries.
Project-URL: Repository, https://github.com/HrishiDhondge/unipdb_mapper.git
Project-URL: Bug Tracker, https://github.com/HrishiDhondge/unipdb_mapper/issues
Author-email: Hrishikesh DHONDGE <hbdhondge@gmail.com>
License-Expression: MIT
License-File: LICENSE
Keywords: PDB,UniProt,mapper,numbering,residue
Requires-Python: >=3.11
Requires-Dist: bs4>=0.0.2
Requires-Dist: lxml>=5.3.2
Requires-Dist: pytest>=8.3.5
Requires-Dist: requests-mock>=1.12.1
Requires-Dist: sh>=2.2.2
Requires-Dist: wget>=3.2
